daisys_mcp/__init__.py
daisys_mcp/http_tts.py
daisys_mcp/model.py
daisys_mcp/server.py
daisys_mcp/utils.py
daisys_mcp/websocket_tts.py
daisys_mcp-1.0.3.dist-info/METADATA
daisys_mcp-1.0.3.dist-info/WHEEL
daisys_mcp-1.0.3.dist-info/entry_points.txt
daisys_mcp-1.0.3.dist-info/top_level.txt
daisys_mcp-1.0.3.dist-info/RECORD
