Metadata-Version: 2.4
Name: daisys-mcp
Version: 1.0.3
Summary: Daisys MCP Server
Author-email: Jasper Jumelet <jasper@daisys.ai>
Requires-Python: >=3.10
Requires-Dist: daisys>=1.1.0
Requires-Dist: httpx-ws>=0.7.2
Requires-Dist: mcp>=1.6.0
Requires-Dist: mcp[cli]==1.6
Requires-Dist: numpy>=2.2.5
Requires-Dist: pyaudio>=0.2.14
Requires-Dist: pydantic>=2.10.6
Requires-Dist: sounddevice>=0.5.1
Requires-Dist: soundfile>=0.13.1
Requires-Dist: wave>=0.0.2
Provides-Extra: dev
Requires-Dist: pytest>=8.0.0; extra == "dev"
Requires-Dist: pytest-asyncio>=0.23.8; extra == "dev"
Requires-Dist: pre-commit==3.6.2; extra == "dev"
Requires-Dist: ruff==0.3.0; extra == "dev"
Requires-Dist: fastmcp==0.4.1; extra == "dev"
Requires-Dist: twine==6.1.0; extra == "dev"
Requires-Dist: pytest==8.0.0; extra == "dev"
Requires-Dist: build>=1.0.3; extra == "dev"
